{"file:///c%3A/Users/Angelo/source/repos/Black%20Jack%20Game/Black%20Jack%20Game/MainWindow.xaml":{"language":"XML","code":87,"comment":4,"blank":23},"file:///c%3A/Users/Angelo/source/repos/Black%20Jack%20Game/Black%20Jack%20Game/Player.cs":{"language":"C#","code":108,"comment":0,"blank":31},"file:///c%3A/Users/Angelo/source/repos/Black%20Jack%20Game/Black%20Jack%20Game/Table.cs":{"language":"C#","code":26,"comment":0,"blank":8},"file:///c%3A/Users/Angelo/source/repos/Black%20Jack%20Game/Black%20Jack%20Game/Deck.cs":{"language":"C#","code":127,"comment":0,"blank":37},"file:///c%3A/Users/Angelo/source/repos/Black%20Jack%20Game/Black%20Jack%20Game/CardTools.cs":{"language":"C#","code":86,"comment":0,"blank":25},"file:///c%3A/Users/Angelo/source/repos/Black%20Jack%20Game/Black%20Jack%20Game/MainWindow.xaml.cs":{"language":"C#","code":359,"comment":5,"blank":100},"file:///c%3A/Users/Angelo/source/repos/Black%20Jack%20Game/Black%20Jack%20Game/Black%20Jack%20Game.csproj":{"language":"XML","code":103,"comment":0,"blank":0},"file:///c%3A/Users/Angelo/source/repos/Black%20Jack%20Game/Black%20Jack%20Game/Card.cs":{"language":"C#","code":68,"comment":0,"blank":23},"file:///c%3A/Users/Angelo/source/repos/Black%20Jack%20Game/Black%20Jack%20Game/App.xaml":{"language":"XML","code":8,"comment":0,"blank":2},"file:///c%3A/Users/Angelo/source/repos/Black%20Jack%20Game/Black%20Jack%20Game/Properties/Settings.Designer.cs":{"language":"C#","code":16,"comment":9,"blank":6},"file:///c%3A/Users/Angelo/source/repos/Black%20Jack%20Game/Black%20Jack%20Game/Properties/AssemblyInfo.cs":{"language":"C#","code":20,"comment":27,"blank":9},"file:///c%3A/Users/Angelo/source/repos/Black%20Jack%20Game/Black%20Jack%20Game/obj/Debug/App.g.i.cs":{"language":"C#","code":42,"comment":18,"blank":11},"file:///c%3A/Users/Angelo/source/repos/Black%20Jack%20Game/Black%20Jack%20Game/App.xaml.cs":{"language":"C#","code":13,"comment":3,"blank":2},"file:///c%3A/Users/Angelo/source/repos/Black%20Jack%20Game/Black%20Jack%20Game/obj/Debug/.NETFramework%2CVersion%3Dv4.7.2.AssemblyAttributes.cs":{"language":"C#","code":3,"comment":1,"blank":1},"file:///c%3A/Users/Angelo/source/repos/Black%20Jack%20Game/Black%20Jack%20Game/Properties/Resources.Designer.cs":{"language":"C#","code":40,"comment":23,"blank":9},"file:///c%3A/Users/Angelo/source/repos/Black%20Jack%20Game/Black%20Jack%20Game/obj/Debug/App.g.cs":{"language":"C#","code":42,"comment":18,"blank":11},"file:///c%3A/Users/Angelo/source/repos/Black%20Jack%20Game/Black%20Jack%20Game/obj/Debug/MainWindow.g.i.cs":{"language":"C#","code":304,"comment":15,"blank":109},"file:///c%3A/Users/Angelo/source/repos/Black%20Jack%20Game/Black%20Jack%20Game/obj/Debug/MainWindow.g.cs":{"language":"C#","code":304,"comment":15,"blank":109}}